kis2/__init__.py
kis2/kis.py
kis2/htdocs/bind.js
kis2/htdocs/bluebird.min.js
kis2/htdocs/kis.js
KeepInterfaceSimple2Plugin-2.5.dist-info/COPYING
KeepInterfaceSimple2Plugin-2.5.dist-info/METADATA
KeepInterfaceSimple2Plugin-2.5.dist-info/WHEEL
KeepInterfaceSimple2Plugin-2.5.dist-info/entry_points.txt
KeepInterfaceSimple2Plugin-2.5.dist-info/top_level.txt
KeepInterfaceSimple2Plugin-2.5.dist-info/RECORD
